pylabeladjust/__init__.py
pylabeladjust/core.py
pylabeladjust-0.1.12.dist-info/LICENSE
pylabeladjust-0.1.12.dist-info/METADATA
pylabeladjust-0.1.12.dist-info/WHEEL
pylabeladjust-0.1.12.dist-info/RECORD
