Metadata-Version: 2.1
Name: pylabeladjust
Version: 0.1.12
Summary: `pylabeladjust` is a port of Gephi's Label-Adjust algorithm to python.
License: GPL-3.0
Author: MNoichl
Author-email: noichlmax@hotmail.co.uk
Requires-Python: >=3.10,<4.0
Classifier: License :: OSI Approved :: GNU General Public License v3 (GPLv3)
Classifier: Programming Language :: Python :: 3
Classifier: Programming Language :: Python :: 3.10
Classifier: Programming Language :: Python :: 3.11
Classifier: Programming Language :: Python :: 3.12
Requires-Dist: Pyqtree (>=1.0.0,<2.0.0)
Requires-Dist: matplotlib (>=3.7.1,<4.0.0)
Requires-Dist: pandas (>=2.0.3,<3.0.0)
Requires-Dist: tqdm (>=4.66.2,<5.0.0)
Project-URL: Homepage, https://github.com/MNoichl/pylabeladjust
